{
	"file_path": "C:\\Users\\gekoc\\AppData\\Local\\Packages\\Microsoft.MinecraftUWP_8wekyb3d8bbwe\\LocalState\\games\\com.mojang\\development_behavior_packs\\Cave Enhancements BP\\recipes\\dynamite.json",
	"file_type": "recipe",
	"format_version": 1,
	"file_uuid": "3c620c03_8726_4ecb_8385_56533d709a32",
	"file_version": 1,
	"cache_content": {
		"is_minified": true,
		"children": {
			"format_version": "1.16.200",
			"minecraft:recipe_shaped": {
				"description": {
					"identifier": "ores:dynamite"
				},
				"tags": [
					"crafting_table"
				],
				"pattern": [
					" RS",
					"RGR",
					"RR "
				],
				"key": {
					"R": {
						"item": "minecraft:concrete",
						"data": 14
					},
					"S": {
						"item": "minecraft:string"
					},
					"G": {
						"item": "minecraft:gunpowder"
					}
				},
				"result": [
					{
						"item": "ores:dynamite_item"
					}
				]
			}
		}
	}
}